orfmine/__init__.py
orfmine/orfdate/__init__.py
orfmine/orfdate/orfdate.py
orfmine/orfdate/orfdate_original.py
orfmine/orfdate/lib/__init__.py
orfmine/orfdate/lib/arguments.py
orfmine/orfold/__init__.py
orfmine/orfold/orfold.py
orfmine/orfold/data/globular.tab
orfmine/orfold/lib/arguments.py
orfmine/orfold/lib/utils.py
orfmine/orfold/scripts/external_software.py
orfmine/orfold/scripts/orfplot.py
orfmine/orfribo/Snakefile
orfmine/orfribo/__init__.py
orfmine/orfribo/config.yaml
orfmine/orfribo/orfribo.py
orfmine/orfribo/Rscripts/find_adapter_sequence.R
orfmine/orfribo/Rscripts/find_adapter_sequence_original.R
orfmine/orfribo/Rscripts/install_dependencies.R
orfmine/orfribo/Rscripts/periodicity_riboWaltz_exome.R
orfmine/orfribo/Rscripts/periodicity_riboWaltz_exome_original.R
orfmine/orfribo/Rscripts/ribowaltz_psite_with_NA_control.R
orfmine/orfribo/lib/__init__.py
orfmine/orfribo/lib/argparser.py
orfmine/orfribo/lib/biobjects.py
orfmine/orfribo/lib/constants.py
orfmine/orfribo/lib/gffutils.py
orfmine/orfribo/lib/loaders.py
orfmine/orfribo/lib/noncoding_objects.py
orfmine/orfribo/lib/sambam.py
orfmine/orfribo/lib/sequtils.py
orfmine/orfribo/lib/utils.py
orfmine/orfribo/scripts/BAM2Reads.py
orfmine/orfribo/scripts/ORFget.py
orfmine/orfribo/scripts/ORFstats.py
orfmine/orfribo/scripts/__init__.py
orfmine/orfribo/scripts/argparser.py
orfmine/orfribo/scripts/biobjects.py
orfmine/orfribo/scripts/concatenate.py
orfmine/orfribo/scripts/constants.py
orfmine/orfribo/scripts/gffutils.py
orfmine/orfribo/scripts/loaders.py
orfmine/orfribo/scripts/noncoding_objects.py
orfmine/orfribo/scripts/parallel.py
orfmine/orfribo/scripts/report.py
orfmine/orfribo/scripts/sambam.py
orfmine/orfribo/scripts/selected_length.py
orfmine/orfribo/scripts/sequtils.py
orfmine/orfribo/scripts/utils.py
orfmine/orftrack/__init__.py
orfmine/orftrack/orftrack.py
orfmine/orftrack/lib/__init__.py
orfmine/orftrack/lib/fasta_parser.py
orfmine/orftrack/lib/gff_parser.py
orfmine/orftrack/lib/inspect.py
orfmine-3.0.17.dist-info/licenses/LICENSE.md
orfmine-3.0.17.dist-info/METADATA
orfmine-3.0.17.dist-info/WHEEL
orfmine-3.0.17.dist-info/entry_points.txt
orfmine-3.0.17.dist-info/top_level.txt
orfmine-3.0.17.dist-info/RECORD
