Metadata-Version: 2.4
Name: orfmine
Version: 3.0.17
Requires-Python: >=3.9
License-File: LICENSE.md
Requires-Dist: biopython==1.79
Requires-Dist: cairocffi==1.7.1
Requires-Dist: cairosvg==2.7.1
Requires-Dist: contourpy==1.3.0
Requires-Dist: cssselect2==0.7.0
Requires-Dist: cycler==0.12.1
Requires-Dist: defusedxml==0.7.1
Requires-Dist: ete3==3.1.3
Requires-Dist: fonttools==4.54.1
Requires-Dist: freetype-py==2.5.1
Requires-Dist: kiwisolver==1.4.7
Requires-Dist: lightgbm==4.5.0
Requires-Dist: matplotlib==3.9.2
Requires-Dist: pillow==10.4.0
Requires-Dist: scipy==1.13.1
Requires-Dist: seaborn==0.13.2
Requires-Dist: tinycss2==1.3.0
Requires-Dist: webencodings==0.5.1
Requires-Dist: snakemake==7.16.0
Requires-Dist: multiqc==1.25.1
Requires-Dist: DendroPy==4.5.2
Requires-Dist: PyQt5==5.15.11
Requires-Dist: pulp==2.7.0
Dynamic: license-file
Dynamic: requires-dist
Dynamic: requires-python
